ai_proto_server/__init__.py
ai_proto_server/__main__.py
ai_proto_server/encoder.py
ai_proto_server/typing_utils.py
ai_proto_server/util.py
ai_proto_server/controllers/__init__.py
ai_proto_server/controllers/coding_controller.py
ai_proto_server/controllers/dev_controller.py
ai_proto_server/controllers/security_controller_.py
ai_proto_server/models/__init__.py
ai_proto_server/models/api_coding_complete_lang_post_request.py
ai_proto_server/models/api_coding_convert_lang_post_request.py
ai_proto_server/models/api_coding_explain_lang_post_request.py
ai_proto_server/models/api_coding_fix_error_lang_post_request.py
ai_proto_server/models/api_dev_gen_token_cap_get200_response.py
ai_proto_server/models/api_dev_gen_token_post200_response.py
ai_proto_server/models/api_dev_gen_token_post_request.py
ai_proto_server/models/base_model_.py
ai_proto_server/models/err_info.py
ai_proto_server/models/lang.py
ai_proto_server/openapi/openapi.yaml
ai_proto_server/test/__init__.py
ai_proto_server/test/test_coding_controller.py
ai_proto_server/test/test_dev_controller.py
ai_proto_server-0.0.1.dist-info/METADATA
ai_proto_server-0.0.1.dist-info/WHEEL
ai_proto_server-0.0.1.dist-info/entry_points.txt
ai_proto_server-0.0.1.dist-info/top_level.txt
ai_proto_server-0.0.1.dist-info/RECORD
