Metadata-Version: 2.1
Name: ai-proto-server
Version: 0.0.1
Summary: ai-proto
Home-page: UNKNOWN
Author-email: panleiming@linksaas.pro
License: UNKNOWN
Keywords: OpenAPI,ai-proto
Platform: UNKNOWN
Requires-Dist: connexion (>=2.0.2)
Requires-Dist: python-dateutil (>=2.6.0)
Requires-Dist: swagger-ui-bundle (>=0.0.2)
